deltares_wave_toolbox/Style.mplstyle
deltares_wave_toolbox/__init__.py
deltares_wave_toolbox/cores/__init__.py
deltares_wave_toolbox/cores/core_dispersion.py
deltares_wave_toolbox/cores/core_engine.py
deltares_wave_toolbox/cores/core_spectral.py
deltares_wave_toolbox/cores/core_time.py
deltares_wave_toolbox/cores/core_wave_decomposition.py
deltares_wave_toolbox/cores/core_wavefunctions.py
deltares_wave_toolbox/series.py
deltares_wave_toolbox/spectrum.py
deltares_wave_toolbox-1.1.1.dist-info/AUTHORS.rst
deltares_wave_toolbox-1.1.1.dist-info/LICENSE
deltares_wave_toolbox-1.1.1.dist-info/METADATA
deltares_wave_toolbox-1.1.1.dist-info/WHEEL
deltares_wave_toolbox-1.1.1.dist-info/RECORD
