Metadata-Version: 2.3
Name: deltares_wave_toolbox
Version: 1.1.1
Summary: A Python toolbox for wave analysis
License: GPL-3.0-or-later
Author: Jan Kramer
Author-email: jan.kramer@deltares.nl
Requires-Python: >=3.10
Classifier: Development Status :: 5 - Production/Stable
Classifier: Intended Audience :: Science/Research
Classifier: License :: OSI Approved :: GNU General Public License v3 or later (GPLv3+)
Classifier: Natural Language :: English
Classifier: Programming Language :: Python :: 3
Classifier: Programming Language :: Python :: 3.10
Classifier: Programming Language :: Python :: 3.11
Classifier: Programming Language :: Python :: 3.12
Classifier: Programming Language :: Python :: 3.13
Requires-Dist: matplotlib (>=3.10.0,<4.0.0)
Requires-Dist: numpy (>=2.2.3,<3.0.0)
Requires-Dist: scipy (>=1.14.0)
Project-URL: Documentation, https://deltares-wave-toolbox.readthedocs.io
Project-URL: Repository, https://github.com/Deltares-research/wave-toolbox
